mcp_llms_txt/__init__.py
mcp_llms_txt/server.py
mcp_llms_txt-0.2.0.dist-info/METADATA
mcp_llms_txt-0.2.0.dist-info/WHEEL
mcp_llms_txt-0.2.0.dist-info/entry_points.txt
mcp_llms_txt-0.2.0.dist-info/licenses/LICENSE
mcp_llms_txt-0.2.0.dist-info/RECORD
